lavender_pyacan/__init__.py
lavender_pyacan/nation/__init__.py
lavender_pyacan/nation/nation.py
Lavender_Pyacan-1.0.0.dist-info/LICENSE
Lavender_Pyacan-1.0.0.dist-info/METADATA
Lavender_Pyacan-1.0.0.dist-info/WHEEL
Lavender_Pyacan-1.0.0.dist-info/top_level.txt
Lavender_Pyacan-1.0.0.dist-info/RECORD
